declaro/__init__.py
declaro-0.0.1.dist-info/METADATA
declaro-0.0.1.dist-info/WHEEL
declaro-0.0.1.dist-info/licenses/LICENSE
declaro-0.0.1.dist-info/RECORD
