Metadata-Version: 2.4
Name: declaro
Version: 0.0.1
Summary: The Functional Python Stack - pure functions, typed data, no class magic
Project-URL: Homepage, https://github.com/adamzwasserman/declaro
Project-URL: Documentation, https://github.com/adamzwasserman/declaro
Project-URL: Repository, https://github.com/adamzwasserman/declaro
Author: Adam Zachary Wasserman
License-Expression: MIT
License-File: LICENSE
Keywords: database,functional,pure-functions,schema,typing,validation
Classifier: Development Status :: 1 - Planning
Classifier: Intended Audience :: Developers
Classifier: License :: OSI Approved :: MIT License
Classifier: Programming Language :: Python :: 3
Classifier: Programming Language :: Python :: 3.11
Classifier: Programming Language :: Python :: 3.12
Classifier: Programming Language :: Python :: 3.13
Classifier: Topic :: Software Development :: Libraries :: Python Modules
Classifier: Typing :: Typed
Requires-Python: >=3.11
Provides-Extra: all
Requires-Dist: declaro-api; extra == 'all'
Requires-Dist: declaro-persistum; extra == 'all'
Requires-Dist: declaro-ximenez; extra == 'all'
Provides-Extra: api
Requires-Dist: declaro-api; extra == 'api'
Provides-Extra: persistum
Requires-Dist: declaro-persistum; extra == 'persistum'
Provides-Extra: ximenez
Requires-Dist: declaro-ximenez; extra == 'ximenez'
